{
    "method": "latentnerf",
    "aspect": "color",
    "prompt_name": "A_turquoise_desk_with_brass_handle",
    "individual_scores": {
        "rgb_0.png": 0.3333333333333333,
        "rgb_10.png": 0.3333333333333333,
        "rgb_20.png": 0.3333333333333333,
        "rgb_30.png": 0.3333333333333333,
        "rgb_40.png": 0.5,
        "rgb_50.png": 0.3333333333333333,
        "rgb_60.png": 0.3333333333333333,
        "rgb_70.png": 0.5,
        "rgb_80.png": 0.5,
        "rgb_90.png": 0.3333333333333333,
        "rgb_100.png": 0.3333333333333333,
        "rgb_110.png": 0.5
    },
    "average_tifa_score": 0.3888888888888889,
    "question_logs": [
        {
            "image": "rgb_0.png",
            "ques_ans": {
                "Is this a desk?": {
                    "caption": "A turquoise desk with brass handle",
                    "element": "desk",
                    "question": "Is this a desk?",
                    "choices": [
                        "yes",
                        "no"
                    ],
                    "answer": "yes",
                    "element_type": "object",
                    "free_form_vqa": "no",
                    "multiple_choice_vqa": "no",
                    "scores": 0
                },
                "What type of furniture is shown?": {
                    "caption": "A turquoise desk with brass handle",
                    "element": "desk",
                    "question": "What type of furniture is shown?",
                    "choices": [
                        "desk",
                        "table",
                        "chair",
                        "cabinet"
                    ],
                    "answer": "desk",
                    "element_type": "object",
                    "free_form_vqa": "side table",
                    "multiple_choice_vqa": "table",
                    "scores": 0
                },
                "Is the desk turquoise?": {
                    "caption": "A turquoise desk with brass handle",
                    "element": "turquoise",
                    "question": "Is the desk turquoise?",
                    "choices": [
                        "yes",
                        "no"
                    ],
                    "answer": "yes",
                    "element_type": "color",
                    "free_form_vqa": "yes",
                    "multiple_choice_vqa": "yes",
                    "scores": 1
                },
                "What color is the desk?": {
                    "caption": "A turquoise desk with brass handle",
                    "element": "turquoise",
                    "question": "What color is the desk?",
                    "choices": [
                        "turquoise",
                        "red",
                        "blue",
                        "green"
                    ],
                    "answer": "turquoise",
                    "element_type": "color",
                    "free_form_vqa": "blue",
                    "multiple_choice_vqa": "blue",
                    "scores": 0
                },
                "Does the desk have a brass handle?": {
                    "caption": "A turquoise desk with brass handle",
                    "element": "brass handle",
                    "question": "Does the desk have a brass handle?",
                    "choices": [
                        "yes",
                        "no"
                    ],
                    "answer": "yes",
                    "element_type": "attribute",
                    "free_form_vqa": "yes",
                    "multiple_choice_vqa": "yes",
                    "scores": 1
                },
                "What material is the handle made of?": {
                    "caption": "A turquoise desk with brass handle",
                    "element": "brass handle",
                    "question": "What material is the handle made of?",
                    "choices": [
                        "brass",
                        "silver",
                        "plastic",
                        "wood"
                    ],
                    "answer": "brass",
                    "element_type": "attribute",
                    "free_form_vqa": "gold",
                    "multiple_choice_vqa": "silver",
                    "scores": 0
                }
            }
        },
        {
            "image": "rgb_10.png",
            "ques_ans": {
                "Is this a desk?": {
                    "caption": "A turquoise desk with brass handle",
                    "element": "desk",
                    "question": "Is this a desk?",
                    "choices": [
                        "yes",
                        "no"
                    ],
                    "answer": "yes",
                    "element_type": "object",
                    "free_form_vqa": "no",
                    "multiple_choice_vqa": "no",
                    "scores": 0
                },
                "What type of furniture is shown?": {
                    "caption": "A turquoise desk with brass handle",
                    "element": "desk",
                    "question": "What type of furniture is shown?",
                    "choices": [
                        "desk",
                        "table",
                        "chair",
                        "cabinet"
                    ],
                    "answer": "desk",
                    "element_type": "object",
                    "free_form_vqa": "side table",
                    "multiple_choice_vqa": "table",
                    "scores": 0
                },
                "Is the desk turquoise?": {
                    "caption": "A turquoise desk with brass handle",
                    "element": "turquoise",
                    "question": "Is the desk turquoise?",
                    "choices": [
                        "yes",
                        "no"
                    ],
                    "answer": "yes",
                    "element_type": "color",
                    "free_form_vqa": "yes",
                    "multiple_choice_vqa": "yes",
                    "scores": 1
                },
                "What color is the desk?": {
                    "caption": "A turquoise desk with brass handle",
                    "element": "turquoise",
                    "question": "What color is the desk?",
                    "choices": [
                        "turquoise",
                        "red",
                        "blue",
                        "green"
                    ],
                    "answer": "turquoise",
                    "element_type": "color",
                    "free_form_vqa": "blue",
                    "multiple_choice_vqa": "blue",
                    "scores": 0
                },
                "Does the desk have a brass handle?": {
                    "caption": "A turquoise desk with brass handle",
                    "element": "brass handle",
                    "question": "Does the desk have a brass handle?",
                    "choices": [
                        "yes",
                        "no"
                    ],
                    "answer": "yes",
                    "element_type": "attribute",
                    "free_form_vqa": "yes",
                    "multiple_choice_vqa": "yes",
                    "scores": 1
                },
                "What material is the handle made of?": {
                    "caption": "A turquoise desk with brass handle",
                    "element": "brass handle",
                    "question": "What material is the handle made of?",
                    "choices": [
                        "brass",
                        "silver",
                        "plastic",
                        "wood"
                    ],
                    "answer": "brass",
                    "element_type": "attribute",
                    "free_form_vqa": "gold",
                    "multiple_choice_vqa": "silver",
                    "scores": 0
                }
            }
        },
        {
            "image": "rgb_20.png",
            "ques_ans": {
                "Is this a desk?": {
                    "caption": "A turquoise desk with brass handle",
                    "element": "desk",
                    "question": "Is this a desk?",
                    "choices": [
                        "yes",
                        "no"
                    ],
                    "answer": "yes",
                    "element_type": "object",
                    "free_form_vqa": "no",
                    "multiple_choice_vqa": "no",
                    "scores": 0
                },
                "What type of furniture is shown?": {
                    "caption": "A turquoise desk with brass handle",
                    "element": "desk",
                    "question": "What type of furniture is shown?",
                    "choices": [
                        "desk",
                        "table",
                        "chair",
                        "cabinet"
                    ],
                    "answer": "desk",
                    "element_type": "object",
                    "free_form_vqa": "side table",
                    "multiple_choice_vqa": "table",
                    "scores": 0
                },
                "Is the desk turquoise?": {
                    "caption": "A turquoise desk with brass handle",
                    "element": "turquoise",
                    "question": "Is the desk turquoise?",
                    "choices": [
                        "yes",
                        "no"
                    ],
                    "answer": "yes",
                    "element_type": "color",
                    "free_form_vqa": "yes",
                    "multiple_choice_vqa": "yes",
                    "scores": 1
                },
                "What color is the desk?": {
                    "caption": "A turquoise desk with brass handle",
                    "element": "turquoise",
                    "question": "What color is the desk?",
                    "choices": [
                        "turquoise",
                        "red",
                        "blue",
                        "green"
                    ],
                    "answer": "turquoise",
                    "element_type": "color",
                    "free_form_vqa": "blue",
                    "multiple_choice_vqa": "blue",
                    "scores": 0
                },
                "Does the desk have a brass handle?": {
                    "caption": "A turquoise desk with brass handle",
                    "element": "brass handle",
                    "question": "Does the desk have a brass handle?",
                    "choices": [
                        "yes",
                        "no"
                    ],
                    "answer": "yes",
                    "element_type": "attribute",
                    "free_form_vqa": "yes",
                    "multiple_choice_vqa": "yes",
                    "scores": 1
                },
                "What material is the handle made of?": {
                    "caption": "A turquoise desk with brass handle",
                    "element": "brass handle",
                    "question": "What material is the handle made of?",
                    "choices": [
                        "brass",
                        "silver",
                        "plastic",
                        "wood"
                    ],
                    "answer": "brass",
                    "element_type": "attribute",
                    "free_form_vqa": "gold",
                    "multiple_choice_vqa": "silver",
                    "scores": 0
                }
            }
        },
        {
            "image": "rgb_30.png",
            "ques_ans": {
                "Is this a desk?": {
                    "caption": "A turquoise desk with brass handle",
                    "element": "desk",
                    "question": "Is this a desk?",
                    "choices": [
                        "yes",
                        "no"
                    ],
                    "answer": "yes",
                    "element_type": "object",
                    "free_form_vqa": "no",
                    "multiple_choice_vqa": "no",
                    "scores": 0
                },
                "What type of furniture is shown?": {
                    "caption": "A turquoise desk with brass handle",
                    "element": "desk",
                    "question": "What type of furniture is shown?",
                    "choices": [
                        "desk",
                        "table",
                        "chair",
                        "cabinet"
                    ],
                    "answer": "desk",
                    "element_type": "object",
                    "free_form_vqa": "side table",
                    "multiple_choice_vqa": "table",
                    "scores": 0
                },
                "Is the desk turquoise?": {
                    "caption": "A turquoise desk with brass handle",
                    "element": "turquoise",
                    "question": "Is the desk turquoise?",
                    "choices": [
                        "yes",
                        "no"
                    ],
                    "answer": "yes",
                    "element_type": "color",
                    "free_form_vqa": "yes",
                    "multiple_choice_vqa": "yes",
                    "scores": 1
                },
                "What color is the desk?": {
                    "caption": "A turquoise desk with brass handle",
                    "element": "turquoise",
                    "question": "What color is the desk?",
                    "choices": [
                        "turquoise",
                        "red",
                        "blue",
                        "green"
                    ],
                    "answer": "turquoise",
                    "element_type": "color",
                    "free_form_vqa": "blue",
                    "multiple_choice_vqa": "blue",
                    "scores": 0
                },
                "Does the desk have a brass handle?": {
                    "caption": "A turquoise desk with brass handle",
                    "element": "brass handle",
                    "question": "Does the desk have a brass handle?",
                    "choices": [
                        "yes",
                        "no"
                    ],
                    "answer": "yes",
                    "element_type": "attribute",
                    "free_form_vqa": "yes",
                    "multiple_choice_vqa": "yes",
                    "scores": 1
                },
                "What material is the handle made of?": {
                    "caption": "A turquoise desk with brass handle",
                    "element": "brass handle",
                    "question": "What material is the handle made of?",
                    "choices": [
                        "brass",
                        "silver",
                        "plastic",
                        "wood"
                    ],
                    "answer": "brass",
                    "element_type": "attribute",
                    "free_form_vqa": "gold",
                    "multiple_choice_vqa": "silver",
                    "scores": 0
                }
            }
        },
        {
            "image": "rgb_40.png",
            "ques_ans": {
                "Is this a desk?": {
                    "caption": "A turquoise desk with brass handle",
                    "element": "desk",
                    "question": "Is this a desk?",
                    "choices": [
                        "yes",
                        "no"
                    ],
                    "answer": "yes",
                    "element_type": "object",
                    "free_form_vqa": "no",
                    "multiple_choice_vqa": "no",
                    "scores": 0
                },
                "What type of furniture is shown?": {
                    "caption": "A turquoise desk with brass handle",
                    "element": "desk",
                    "question": "What type of furniture is shown?",
                    "choices": [
                        "desk",
                        "table",
                        "chair",
                        "cabinet"
                    ],
                    "answer": "desk",
                    "element_type": "object",
                    "free_form_vqa": "side table",
                    "multiple_choice_vqa": "table",
                    "scores": 0
                },
                "Is the desk turquoise?": {
                    "caption": "A turquoise desk with brass handle",
                    "element": "turquoise",
                    "question": "Is the desk turquoise?",
                    "choices": [
                        "yes",
                        "no"
                    ],
                    "answer": "yes",
                    "element_type": "color",
                    "free_form_vqa": "yes",
                    "multiple_choice_vqa": "yes",
                    "scores": 1
                },
                "What color is the desk?": {
                    "caption": "A turquoise desk with brass handle",
                    "element": "turquoise",
                    "question": "What color is the desk?",
                    "choices": [
                        "turquoise",
                        "red",
                        "blue",
                        "green"
                    ],
                    "answer": "turquoise",
                    "element_type": "color",
                    "free_form_vqa": "white",
                    "multiple_choice_vqa": "red",
                    "scores": 0
                },
                "Does the desk have a brass handle?": {
                    "caption": "A turquoise desk with brass handle",
                    "element": "brass handle",
                    "question": "Does the desk have a brass handle?",
                    "choices": [
                        "yes",
                        "no"
                    ],
                    "answer": "yes",
                    "element_type": "attribute",
                    "free_form_vqa": "yes",
                    "multiple_choice_vqa": "yes",
                    "scores": 1
                },
                "What material is the handle made of?": {
                    "caption": "A turquoise desk with brass handle",
                    "element": "brass handle",
                    "question": "What material is the handle made of?",
                    "choices": [
                        "brass",
                        "silver",
                        "plastic",
                        "wood"
                    ],
                    "answer": "brass",
                    "element_type": "attribute",
                    "free_form_vqa": "brass",
                    "multiple_choice_vqa": "brass",
                    "scores": 1
                }
            }
        },
        {
            "image": "rgb_50.png",
            "ques_ans": {
                "Is this a desk?": {
                    "caption": "A turquoise desk with brass handle",
                    "element": "desk",
                    "question": "Is this a desk?",
                    "choices": [
                        "yes",
                        "no"
                    ],
                    "answer": "yes",
                    "element_type": "object",
                    "free_form_vqa": "no",
                    "multiple_choice_vqa": "no",
                    "scores": 0
                },
                "What type of furniture is shown?": {
                    "caption": "A turquoise desk with brass handle",
                    "element": "desk",
                    "question": "What type of furniture is shown?",
                    "choices": [
                        "desk",
                        "table",
                        "chair",
                        "cabinet"
                    ],
                    "answer": "desk",
                    "element_type": "object",
                    "free_form_vqa": "table",
                    "multiple_choice_vqa": "table",
                    "scores": 0
                },
                "Is the desk turquoise?": {
                    "caption": "A turquoise desk with brass handle",
                    "element": "turquoise",
                    "question": "Is the desk turquoise?",
                    "choices": [
                        "yes",
                        "no"
                    ],
                    "answer": "yes",
                    "element_type": "color",
                    "free_form_vqa": "yes",
                    "multiple_choice_vqa": "yes",
                    "scores": 1
                },
                "What color is the desk?": {
                    "caption": "A turquoise desk with brass handle",
                    "element": "turquoise",
                    "question": "What color is the desk?",
                    "choices": [
                        "turquoise",
                        "red",
                        "blue",
                        "green"
                    ],
                    "answer": "turquoise",
                    "element_type": "color",
                    "free_form_vqa": "white",
                    "multiple_choice_vqa": "red",
                    "scores": 0
                },
                "Does the desk have a brass handle?": {
                    "caption": "A turquoise desk with brass handle",
                    "element": "brass handle",
                    "question": "Does the desk have a brass handle?",
                    "choices": [
                        "yes",
                        "no"
                    ],
                    "answer": "yes",
                    "element_type": "attribute",
                    "free_form_vqa": "yes",
                    "multiple_choice_vqa": "yes",
                    "scores": 1
                },
                "What material is the handle made of?": {
                    "caption": "A turquoise desk with brass handle",
                    "element": "brass handle",
                    "question": "What material is the handle made of?",
                    "choices": [
                        "brass",
                        "silver",
                        "plastic",
                        "wood"
                    ],
                    "answer": "brass",
                    "element_type": "attribute",
                    "free_form_vqa": "gold",
                    "multiple_choice_vqa": "silver",
                    "scores": 0
                }
            }
        },
        {
            "image": "rgb_60.png",
            "ques_ans": {
                "Is this a desk?": {
                    "caption": "A turquoise desk with brass handle",
                    "element": "desk",
                    "question": "Is this a desk?",
                    "choices": [
                        "yes",
                        "no"
                    ],
                    "answer": "yes",
                    "element_type": "object",
                    "free_form_vqa": "no",
                    "multiple_choice_vqa": "no",
                    "scores": 0
                },
                "What type of furniture is shown?": {
                    "caption": "A turquoise desk with brass handle",
                    "element": "desk",
                    "question": "What type of furniture is shown?",
                    "choices": [
                        "desk",
                        "table",
                        "chair",
                        "cabinet"
                    ],
                    "answer": "desk",
                    "element_type": "object",
                    "free_form_vqa": "side table",
                    "multiple_choice_vqa": "table",
                    "scores": 0
                },
                "Is the desk turquoise?": {
                    "caption": "A turquoise desk with brass handle",
                    "element": "turquoise",
                    "question": "Is the desk turquoise?",
                    "choices": [
                        "yes",
                        "no"
                    ],
                    "answer": "yes",
                    "element_type": "color",
                    "free_form_vqa": "yes",
                    "multiple_choice_vqa": "yes",
                    "scores": 1
                },
                "What color is the desk?": {
                    "caption": "A turquoise desk with brass handle",
                    "element": "turquoise",
                    "question": "What color is the desk?",
                    "choices": [
                        "turquoise",
                        "red",
                        "blue",
                        "green"
                    ],
                    "answer": "turquoise",
                    "element_type": "color",
                    "free_form_vqa": "blue",
                    "multiple_choice_vqa": "blue",
                    "scores": 0
                },
                "Does the desk have a brass handle?": {
                    "caption": "A turquoise desk with brass handle",
                    "element": "brass handle",
                    "question": "Does the desk have a brass handle?",
                    "choices": [
                        "yes",
                        "no"
                    ],
                    "answer": "yes",
                    "element_type": "attribute",
                    "free_form_vqa": "yes",
                    "multiple_choice_vqa": "yes",
                    "scores": 1
                },
                "What material is the handle made of?": {
                    "caption": "A turquoise desk with brass handle",
                    "element": "brass handle",
                    "question": "What material is the handle made of?",
                    "choices": [
                        "brass",
                        "silver",
                        "plastic",
                        "wood"
                    ],
                    "answer": "brass",
                    "element_type": "attribute",
                    "free_form_vqa": "metal",
                    "multiple_choice_vqa": "plastic",
                    "scores": 0
                }
            }
        },
        {
            "image": "rgb_70.png",
            "ques_ans": {
                "Is this a desk?": {
                    "caption": "A turquoise desk with brass handle",
                    "element": "desk",
                    "question": "Is this a desk?",
                    "choices": [
                        "yes",
                        "no"
                    ],
                    "answer": "yes",
                    "element_type": "object",
                    "free_form_vqa": "no",
                    "multiple_choice_vqa": "no",
                    "scores": 0
                },
                "What type of furniture is shown?": {
                    "caption": "A turquoise desk with brass handle",
                    "element": "desk",
                    "question": "What type of furniture is shown?",
                    "choices": [
                        "desk",
                        "table",
                        "chair",
                        "cabinet"
                    ],
                    "answer": "desk",
                    "element_type": "object",
                    "free_form_vqa": "side table",
                    "multiple_choice_vqa": "table",
                    "scores": 0
                },
                "Is the desk turquoise?": {
                    "caption": "A turquoise desk with brass handle",
                    "element": "turquoise",
                    "question": "Is the desk turquoise?",
                    "choices": [
                        "yes",
                        "no"
                    ],
                    "answer": "yes",
                    "element_type": "color",
                    "free_form_vqa": "yes",
                    "multiple_choice_vqa": "yes",
                    "scores": 1
                },
                "What color is the desk?": {
                    "caption": "A turquoise desk with brass handle",
                    "element": "turquoise",
                    "question": "What color is the desk?",
                    "choices": [
                        "turquoise",
                        "red",
                        "blue",
                        "green"
                    ],
                    "answer": "turquoise",
                    "element_type": "color",
                    "free_form_vqa": "blue",
                    "multiple_choice_vqa": "blue",
                    "scores": 0
                },
                "Does the desk have a brass handle?": {
                    "caption": "A turquoise desk with brass handle",
                    "element": "brass handle",
                    "question": "Does the desk have a brass handle?",
                    "choices": [
                        "yes",
                        "no"
                    ],
                    "answer": "yes",
                    "element_type": "attribute",
                    "free_form_vqa": "yes",
                    "multiple_choice_vqa": "yes",
                    "scores": 1
                },
                "What material is the handle made of?": {
                    "caption": "A turquoise desk with brass handle",
                    "element": "brass handle",
                    "question": "What material is the handle made of?",
                    "choices": [
                        "brass",
                        "silver",
                        "plastic",
                        "wood"
                    ],
                    "answer": "brass",
                    "element_type": "attribute",
                    "free_form_vqa": "brass",
                    "multiple_choice_vqa": "brass",
                    "scores": 1
                }
            }
        },
        {
            "image": "rgb_80.png",
            "ques_ans": {
                "Is this a desk?": {
                    "caption": "A turquoise desk with brass handle",
                    "element": "desk",
                    "question": "Is this a desk?",
                    "choices": [
                        "yes",
                        "no"
                    ],
                    "answer": "yes",
                    "element_type": "object",
                    "free_form_vqa": "no",
                    "multiple_choice_vqa": "no",
                    "scores": 0
                },
                "What type of furniture is shown?": {
                    "caption": "A turquoise desk with brass handle",
                    "element": "desk",
                    "question": "What type of furniture is shown?",
                    "choices": [
                        "desk",
                        "table",
                        "chair",
                        "cabinet"
                    ],
                    "answer": "desk",
                    "element_type": "object",
                    "free_form_vqa": "side table",
                    "multiple_choice_vqa": "table",
                    "scores": 0
                },
                "Is the desk turquoise?": {
                    "caption": "A turquoise desk with brass handle",
                    "element": "turquoise",
                    "question": "Is the desk turquoise?",
                    "choices": [
                        "yes",
                        "no"
                    ],
                    "answer": "yes",
                    "element_type": "color",
                    "free_form_vqa": "yes",
                    "multiple_choice_vqa": "yes",
                    "scores": 1
                },
                "What color is the desk?": {
                    "caption": "A turquoise desk with brass handle",
                    "element": "turquoise",
                    "question": "What color is the desk?",
                    "choices": [
                        "turquoise",
                        "red",
                        "blue",
                        "green"
                    ],
                    "answer": "turquoise",
                    "element_type": "color",
                    "free_form_vqa": "blue and gold",
                    "multiple_choice_vqa": "blue",
                    "scores": 0
                },
                "Does the desk have a brass handle?": {
                    "caption": "A turquoise desk with brass handle",
                    "element": "brass handle",
                    "question": "Does the desk have a brass handle?",
                    "choices": [
                        "yes",
                        "no"
                    ],
                    "answer": "yes",
                    "element_type": "attribute",
                    "free_form_vqa": "yes",
                    "multiple_choice_vqa": "yes",
                    "scores": 1
                },
                "What material is the handle made of?": {
                    "caption": "A turquoise desk with brass handle",
                    "element": "brass handle",
                    "question": "What material is the handle made of?",
                    "choices": [
                        "brass",
                        "silver",
                        "plastic",
                        "wood"
                    ],
                    "answer": "brass",
                    "element_type": "attribute",
                    "free_form_vqa": "brass",
                    "multiple_choice_vqa": "brass",
                    "scores": 1
                }
            }
        },
        {
            "image": "rgb_90.png",
            "ques_ans": {
                "Is this a desk?": {
                    "caption": "A turquoise desk with brass handle",
                    "element": "desk",
                    "question": "Is this a desk?",
                    "choices": [
                        "yes",
                        "no"
                    ],
                    "answer": "yes",
                    "element_type": "object",
                    "free_form_vqa": "no",
                    "multiple_choice_vqa": "no",
                    "scores": 0
                },
                "What type of furniture is shown?": {
                    "caption": "A turquoise desk with brass handle",
                    "element": "desk",
                    "question": "What type of furniture is shown?",
                    "choices": [
                        "desk",
                        "table",
                        "chair",
                        "cabinet"
                    ],
                    "answer": "desk",
                    "element_type": "object",
                    "free_form_vqa": "side table",
                    "multiple_choice_vqa": "table",
                    "scores": 0
                },
                "Is the desk turquoise?": {
                    "caption": "A turquoise desk with brass handle",
                    "element": "turquoise",
                    "question": "Is the desk turquoise?",
                    "choices": [
                        "yes",
                        "no"
                    ],
                    "answer": "yes",
                    "element_type": "color",
                    "free_form_vqa": "yes",
                    "multiple_choice_vqa": "yes",
                    "scores": 1
                },
                "What color is the desk?": {
                    "caption": "A turquoise desk with brass handle",
                    "element": "turquoise",
                    "question": "What color is the desk?",
                    "choices": [
                        "turquoise",
                        "red",
                        "blue",
                        "green"
                    ],
                    "answer": "turquoise",
                    "element_type": "color",
                    "free_form_vqa": "blue",
                    "multiple_choice_vqa": "blue",
                    "scores": 0
                },
                "Does the desk have a brass handle?": {
                    "caption": "A turquoise desk with brass handle",
                    "element": "brass handle",
                    "question": "Does the desk have a brass handle?",
                    "choices": [
                        "yes",
                        "no"
                    ],
                    "answer": "yes",
                    "element_type": "attribute",
                    "free_form_vqa": "yes",
                    "multiple_choice_vqa": "yes",
                    "scores": 1
                },
                "What material is the handle made of?": {
                    "caption": "A turquoise desk with brass handle",
                    "element": "brass handle",
                    "question": "What material is the handle made of?",
                    "choices": [
                        "brass",
                        "silver",
                        "plastic",
                        "wood"
                    ],
                    "answer": "brass",
                    "element_type": "attribute",
                    "free_form_vqa": "gold",
                    "multiple_choice_vqa": "silver",
                    "scores": 0
                }
            }
        },
        {
            "image": "rgb_100.png",
            "ques_ans": {
                "Is this a desk?": {
                    "caption": "A turquoise desk with brass handle",
                    "element": "desk",
                    "question": "Is this a desk?",
                    "choices": [
                        "yes",
                        "no"
                    ],
                    "answer": "yes",
                    "element_type": "object",
                    "free_form_vqa": "no",
                    "multiple_choice_vqa": "no",
                    "scores": 0
                },
                "What type of furniture is shown?": {
                    "caption": "A turquoise desk with brass handle",
                    "element": "desk",
                    "question": "What type of furniture is shown?",
                    "choices": [
                        "desk",
                        "table",
                        "chair",
                        "cabinet"
                    ],
                    "answer": "desk",
                    "element_type": "object",
                    "free_form_vqa": "side table",
                    "multiple_choice_vqa": "table",
                    "scores": 0
                },
                "Is the desk turquoise?": {
                    "caption": "A turquoise desk with brass handle",
                    "element": "turquoise",
                    "question": "Is the desk turquoise?",
                    "choices": [
                        "yes",
                        "no"
                    ],
                    "answer": "yes",
                    "element_type": "color",
                    "free_form_vqa": "yes",
                    "multiple_choice_vqa": "yes",
                    "scores": 1
                },
                "What color is the desk?": {
                    "caption": "A turquoise desk with brass handle",
                    "element": "turquoise",
                    "question": "What color is the desk?",
                    "choices": [
                        "turquoise",
                        "red",
                        "blue",
                        "green"
                    ],
                    "answer": "turquoise",
                    "element_type": "color",
                    "free_form_vqa": "blue",
                    "multiple_choice_vqa": "blue",
                    "scores": 0
                },
                "Does the desk have a brass handle?": {
                    "caption": "A turquoise desk with brass handle",
                    "element": "brass handle",
                    "question": "Does the desk have a brass handle?",
                    "choices": [
                        "yes",
                        "no"
                    ],
                    "answer": "yes",
                    "element_type": "attribute",
                    "free_form_vqa": "yes",
                    "multiple_choice_vqa": "yes",
                    "scores": 1
                },
                "What material is the handle made of?": {
                    "caption": "A turquoise desk with brass handle",
                    "element": "brass handle",
                    "question": "What material is the handle made of?",
                    "choices": [
                        "brass",
                        "silver",
                        "plastic",
                        "wood"
                    ],
                    "answer": "brass",
                    "element_type": "attribute",
                    "free_form_vqa": "gold",
                    "multiple_choice_vqa": "silver",
                    "scores": 0
                }
            }
        },
        {
            "image": "rgb_110.png",
            "ques_ans": {
                "Is this a desk?": {
                    "caption": "A turquoise desk with brass handle",
                    "element": "desk",
                    "question": "Is this a desk?",
                    "choices": [
                        "yes",
                        "no"
                    ],
                    "answer": "yes",
                    "element_type": "object",
                    "free_form_vqa": "no",
                    "multiple_choice_vqa": "no",
                    "scores": 0
                },
                "What type of furniture is shown?": {
                    "caption": "A turquoise desk with brass handle",
                    "element": "desk",
                    "question": "What type of furniture is shown?",
                    "choices": [
                        "desk",
                        "table",
                        "chair",
                        "cabinet"
                    ],
                    "answer": "desk",
                    "element_type": "object",
                    "free_form_vqa": "side table",
                    "multiple_choice_vqa": "table",
                    "scores": 0
                },
                "Is the desk turquoise?": {
                    "caption": "A turquoise desk with brass handle",
                    "element": "turquoise",
                    "question": "Is the desk turquoise?",
                    "choices": [
                        "yes",
                        "no"
                    ],
                    "answer": "yes",
                    "element_type": "color",
                    "free_form_vqa": "yes",
                    "multiple_choice_vqa": "yes",
                    "scores": 1
                },
                "What color is the desk?": {
                    "caption": "A turquoise desk with brass handle",
                    "element": "turquoise",
                    "question": "What color is the desk?",
                    "choices": [
                        "turquoise",
                        "red",
                        "blue",
                        "green"
                    ],
                    "answer": "turquoise",
                    "element_type": "color",
                    "free_form_vqa": "blue",
                    "multiple_choice_vqa": "blue",
                    "scores": 0
                },
                "Does the desk have a brass handle?": {
                    "caption": "A turquoise desk with brass handle",
                    "element": "brass handle",
                    "question": "Does the desk have a brass handle?",
                    "choices": [
                        "yes",
                        "no"
                    ],
                    "answer": "yes",
                    "element_type": "attribute",
                    "free_form_vqa": "yes",
                    "multiple_choice_vqa": "yes",
                    "scores": 1
                },
                "What material is the handle made of?": {
                    "caption": "A turquoise desk with brass handle",
                    "element": "brass handle",
                    "question": "What material is the handle made of?",
                    "choices": [
                        "brass",
                        "silver",
                        "plastic",
                        "wood"
                    ],
                    "answer": "brass",
                    "element_type": "attribute",
                    "free_form_vqa": "brass",
                    "multiple_choice_vqa": "brass",
                    "scores": 1
                }
            }
        }
    ]
}